iklayout/__init__.py
iklayout/iklayout.py
iklayout/throttle.py
iklayout-0.0.9.dist-info/METADATA
iklayout-0.0.9.dist-info/WHEEL
iklayout-0.0.9.dist-info/RECORD
