Metadata-Version: 2.4
Name: iklayout
Version: 0.0.9
Summary: 
Author: Jacob Windsor
Author-email: jwindsor@axiomatic-ai.com
Requires-Python: >=3.11,<4.0
Classifier: Programming Language :: Python :: 3
Classifier: Programming Language :: Python :: 3.11
Classifier: Programming Language :: Python :: 3.12
Classifier: Programming Language :: Python :: 3.13
Classifier: Programming Language :: Python :: 3.14
Requires-Dist: ipympl (>=0.9.6,<0.10.0)
Requires-Dist: ipywidgets (>=8.1.5,<9.0.0)
Requires-Dist: klayout (>=0.30,<0.31.0)
Requires-Dist: matplotlib (>=3.10.0,<4.0.0)
Requires-Dist: numpy (>=2.2.0,<3.0.0)
